<annotation>
	<folder>12-31 to 1-3</folder>
	<filename>SY_00009.JPG</filename>
	<path>C:\Users\storm\Documents\2018-2019\cement18-19\12-31 to 1-3\SY_00009.JPG</path>
	<source>
		<database>Unknown</database>
	</source>
	<size>
		<width>4000</width>
		<height>3000</height>
		<depth>3</depth>
	</size>
	<segmented>0</segmented>
	<object>
		<name>motorized</name>
		<pose>Unspecified</pose>
		<truncated>0</truncated>
		<difficult>0</difficult>
		<bndbox>
			<xmin>1485</xmin>
			<ymin>1487</ymin>
			<xmax>1815</xmax>
			<ymax>1692</ymax>
		</bndbox>
	</object>
	<object>
		<name>nonMotorized</name>
		<pose>Unspecified</pose>
		<truncated>0</truncated>
		<difficult>0</difficult>
		<bndbox>
			<xmin>1872</xmin>
			<ymin>1406</ymin>
			<xmax>1948</xmax>
			<ymax>1624</ymax>
		</bndbox>
	</object>
	<object>
		<name>motorized</name>
		<pose>Unspecified</pose>
		<truncated>0</truncated>
		<difficult>0</difficult>
		<bndbox>
			<xmin>2091</xmin>
			<ymin>1457</ymin>
			<xmax>2375</xmax>
			<ymax>1752</ymax>
		</bndbox>
	</object>
</annotation>
